README.md
setup.cfg
setup.py
bsm_model/__init__.py
bsm_model/bsm.py
bsm_model.egg-info/PKG-INFO
bsm_model.egg-info/SOURCES.txt
bsm_model.egg-info/dependency_links.txt
bsm_model.egg-info/requires.txt
bsm_model.egg-info/top_level.txt