Metadata-Version: 1.1
Name: bsm-model
Version: 0.1
Summary: The Black–Scholes–Merton Model calculator in Python.
Home-page: https://qrtt.org
Author: Leopold W.
Author-email: lsw@lwco.com
License: UNKNOWN
Download-URL: https://github.com/leopoldsw/bsm_model/archive/v0.1.tar.gz
Platform: UNKNOWN
